phrydy/__init__.py
phrydy/debug.py
phrydy/doc_generator.py
phrydy/field_docs.py
phrydy/mediafile.py
phrydy/mediafile.pyi
phrydy/mediafile_extended.py
phrydy/py.typed
phrydy-4.1.0.dist-info/LICENSE
phrydy-4.1.0.dist-info/METADATA
phrydy-4.1.0.dist-info/WHEEL
phrydy-4.1.0.dist-info/entry_points.txt
phrydy-4.1.0.dist-info/RECORD
