Metadata-Version: 2.1
Name: phrydy
Version: 4.1.0
Summary: Extended version of the mediafile library of the beets project. It is used by the Python command line tool `audiorename`.
Home-page: https://github.com/Josef-Friedrich/phrydy
License: MIT
Author: Josef Friedrich
Author-email: josef@friedrich.rocks
Requires-Python: >=3.9,<4.0
Classifier: Development Status :: 5 - Production/Stable
Classifier: License :: OSI Approved :: MIT License
Classifier: Programming Language :: Python :: 3
Classifier: Programming Language :: Python :: 3.9
Classifier: Programming Language :: Python :: 3.10
Classifier: Programming Language :: Python :: 3.11
Classifier: Programming Language :: Python :: 3.12
Classifier: Programming Language :: Python :: 3.13
Classifier: Programming Language :: Python :: 3 :: Only
Classifier: Topic :: Utilities
Requires-Dist: filetype (>=1.2.0,<2.0.0)
Requires-Dist: mutagen (>=1.46,<2.0)
Requires-Dist: termcolor (>=2.5,<3.0)
Requires-Dist: typing-extensions (>=4,<5)
Project-URL: Repository, https://github.com/Josef-Friedrich/phrydy
